squeck/VERSION
squeck/__init__.py
squeck/__main__.py
squeck/access_token.py
squeck/common.py
squeck/squeck.py
squeck/widgets/__init__.py
squeck/widgets/env.py
im_squeck-1.1.1.dist-info/LICENSE
im_squeck-1.1.1.dist-info/METADATA
im_squeck-1.1.1.dist-info/WHEEL
im_squeck-1.1.1.dist-info/entry_points.txt
im_squeck-1.1.1.dist-info/top_level.txt
im_squeck-1.1.1.dist-info/RECORD
