Metadata-Version: 2.1
Name: im-squeck
Version: 1.1.1
Summary: The IM Squonk2 Deck (Squeck)
Home-page: https://github.com/informaticsmatters/squonk2-deck
Author: Alan Christie
Author-email: achristie@informaticsmatters.com
License: MIT
Keywords: configuration
Platform: any
Classifier: Development Status :: 5 - Production/Stable
Classifier: Environment :: Console
Classifier: Intended Audience :: Developers
Classifier: License :: OSI Approved :: MIT License
Classifier: Programming Language :: Python :: 3.10
Classifier: Topic :: System :: Installation/Setup
Classifier: Operating System :: POSIX :: Linux
License-File: LICENSE
Requires-Dist: im-squonk2-client (<3.0.0,>=2.2.1)
Requires-Dist: pyyaml (~=6.0)
Requires-Dist: textual (==0.1.18)
